LICENSE
README.md
setup.cfg
setup.py
src/pyqtcaptcha/__init__.py
src/pyqtcaptcha/audio_labels.py
src/pyqtcaptcha/captcha.py
src/pyqtcaptcha/captcha_enums.py
src/pyqtcaptcha/captcha_icon_button.py
src/pyqtcaptcha/captcha_image_button.py
src/pyqtcaptcha/captcha_popup.py
src/pyqtcaptcha/captcha_popup_content.py
src/pyqtcaptcha/captcha_textfield.py
src/pyqtcaptcha/constants.py
src/pyqtcaptcha/image_labels.py
src/pyqtcaptcha/square_labels.py
src/pyqtcaptcha.egg-info/PKG-INFO
src/pyqtcaptcha.egg-info/SOURCES.txt
src/pyqtcaptcha.egg-info/dependency_links.txt
src/pyqtcaptcha.egg-info/entry_points.txt
src/pyqtcaptcha.egg-info/requires.txt
src/pyqtcaptcha.egg-info/top_level.txt
src/pyqtcaptcha/files/audio/1.mp3
src/pyqtcaptcha/files/audio/10.mp3
src/pyqtcaptcha/files/audio/100.mp3
src/pyqtcaptcha/files/audio/1000.mp3
src/pyqtcaptcha/files/audio/1001.mp3
src/pyqtcaptcha/files/audio/1002.mp3
src/pyqtcaptcha/files/audio/1003.mp3
src/pyqtcaptcha/files/audio/1004.mp3
src/pyqtcaptcha/files/audio/1005.mp3
src/pyqtcaptcha/files/audio/1006.mp3
src/pyqtcaptcha/files/audio/1007.mp3
src/pyqtcaptcha/files/audio/1008.mp3
src/pyqtcaptcha/files/audio/1009.mp3
src/pyqtcaptcha/files/audio/101.mp3
src/pyqtcaptcha/files/audio/1010.mp3
src/pyqtcaptcha/files/audio/1011.mp3
src/pyqtcaptcha/files/audio/1012.mp3
src/pyqtcaptcha/files/audio/1013.mp3
src/pyqtcaptcha/files/audio/1014.mp3
src/pyqtcaptcha/files/audio/1015.mp3
src/pyqtcaptcha/files/audio/1016.mp3
src/pyqtcaptcha/files/audio/1017.mp3
src/pyqtcaptcha/files/audio/1018.mp3
src/pyqtcaptcha/files/audio/1019.mp3
src/pyqtcaptcha/files/audio/102.mp3
src/pyqtcaptcha/files/audio/1020.mp3
src/pyqtcaptcha/files/audio/1021.mp3
src/pyqtcaptcha/files/audio/1022.mp3
src/pyqtcaptcha/files/audio/1023.mp3
src/pyqtcaptcha/files/audio/1024.mp3
src/pyqtcaptcha/files/audio/1025.mp3
src/pyqtcaptcha/files/audio/1026.mp3
src/pyqtcaptcha/files/audio/1027.mp3
src/pyqtcaptcha/files/audio/1028.mp3
src/pyqtcaptcha/files/audio/1029.mp3
src/pyqtcaptcha/files/audio/103.mp3
src/pyqtcaptcha/files/audio/1030.mp3
src/pyqtcaptcha/files/audio/1031.mp3
src/pyqtcaptcha/files/audio/1032.mp3
src/pyqtcaptcha/files/audio/1033.mp3
src/pyqtcaptcha/files/audio/1034.mp3
src/pyqtcaptcha/files/audio/1035.mp3
