Metadata-Version: 2.1
Name: pyqtcaptcha
Version: 1.0.0
Summary: A modern and fully customizable CAPTCHA library for PyQt and PySide
Home-page: https://github.com/marcohenning/pyqtcaptcha
Author: Marco Henning
License: MIT
Keywords: python,pyqt,qt,captcha
Classifier: Programming Language :: Python :: 3
Classifier: Operating System :: OS Independent
Classifier: License :: OSI Approved :: MIT License
Requires-Python: >=3.7
License-File: LICENSE
